{
  "briefs": [
    {
      "date": "pending-review",
      "date_display": "",
      "tldr": "",
      "tldr_short": ""
    },
    {
      "date": "decisions",
      "date_display": "",
      "tldr": "",
      "tldr_short": ""
    },
    {
      "date": "2026-04-22",
      "date_display": "Wednesday · Apr 22, 2026",
      "tldr": "**Night-builder #2 shipped.** [BedRock PR #1](https://github.com/Taylorblue123/BedRock/pull/1) — Astro site bolted onto your existing repo, preserving privacy. ⚠️ **Correction:** first draft propagated a CVPR 2026 claim from your old portfolio — you flagged as fake, agent removed it everywhere in the PR. Stale sources still have it (R003).",
      "tldr_short": "BedRock PR #1: Astro site. CVPR claim scrubbed per correction. 2 items in /feedback."
    }
  ]
}